__init__.py
subwaysim/__init__.py
subwaysim/sim.py
subwaysim-0.0.0.dist-info/LICENSE
subwaysim-0.0.0.dist-info/METADATA
subwaysim-0.0.0.dist-info/WHEEL
subwaysim-0.0.0.dist-info/top_level.txt
subwaysim-0.0.0.dist-info/RECORD
