Metadata-Version: 2.1
Name: subwaysim
Version: 0.0.0
Summary: A Python Package for Macroscopic simulation package for urban subway systems
Author-email: Kai Tang <794568794@qq.com>
License: LICENCE
Project-URL: Homepage, https://github.com/zdsjjtTLG/SubwaySim
Keywords: simulation
Classifier: Programming Language :: Python :: 3
Classifier: License :: OSI Approved :: MIT License
Classifier: Operating System :: OS Independent
Requires-Python: >=3.8
License-File: LICENSE
Requires-Dist: geopandas >=0.14.1
Requires-Dist: shapely
Requires-Dist: networkx
Requires-Dist: pandas
Requires-Dist: numpy
Requires-Dist: keplergl
Requires-Dist: geopy
